Detection/__init__.py
image_annotation_streamlit-0.3.4.dist-info/METADATA
image_annotation_streamlit-0.3.4.dist-info/WHEEL
image_annotation_streamlit-0.3.4.dist-info/top_level.txt
image_annotation_streamlit-0.3.4.dist-info/RECORD
