Metadata-Version: 2.1
Name: image_annotation_streamlit
Version: 0.3.4
Summary: streamlit components for image annotation
Home-page: https://github.com/hirune924/Streamlit-Image-Annotation
Author: hirune924
Keywords: Python,Streamlit,React,JavaScript
Requires-Python: >=3.6
Requires-Dist: streamlit >=0.63
